agential/__init__.py
agential/agents/__init__.py
agential/agents/base/__init__.py
agential/agents/base/agent.py
agential/agents/base/modules/__init__.py
agential/agents/base/modules/memory.py
agential/agents/base/modules/reflect.py
agential/agents/base/output.py
agential/agents/base/strategies.py
agential/agents/clin/__init__.py
agential/agents/clin/agent.py
agential/agents/clin/functional.py
agential/agents/clin/memory.py
agential/agents/clin/output.py
agential/agents/clin/prompts.py
agential/agents/clin/strategies/__init__.py
agential/agents/clin/strategies/base.py
agential/agents/clin/strategies/code.py
agential/agents/clin/strategies/general.py
agential/agents/clin/strategies/math.py
agential/agents/clin/strategies/qa.py
agential/agents/critic/__init__.py
agential/agents/critic/agent.py
agential/agents/critic/functional.py
agential/agents/critic/output.py
agential/agents/critic/prompts.py
agential/agents/critic/strategies/__init__.py
agential/agents/critic/strategies/base.py
agential/agents/critic/strategies/code.py
agential/agents/critic/strategies/general.py
agential/agents/critic/strategies/math.py
agential/agents/critic/strategies/qa.py
agential/agents/expel/__init__.py
agential/agents/expel/agent.py
agential/agents/expel/functional.py
agential/agents/expel/memory.py
agential/agents/expel/output.py
agential/agents/expel/prompts.py
agential/agents/expel/strategies/__init__.py
agential/agents/expel/strategies/base.py
agential/agents/expel/strategies/code.py
agential/agents/expel/strategies/general.py
agential/agents/expel/strategies/math.py
agential/agents/expel/strategies/qa.py
agential/agents/lats/__init__.py
agential/agents/lats/agent.py
agential/agents/lats/functional.py
agential/agents/lats/node.py
agential/agents/lats/output.py
agential/agents/lats/prompts.py
agential/agents/lats/strategies/__init__.py
agential/agents/lats/strategies/base.py
agential/agents/lats/strategies/code.py
agential/agents/lats/strategies/general.py
agential-0.2.1.dist-info/LICENSE
agential-0.2.1.dist-info/METADATA
agential-0.2.1.dist-info/WHEEL
agential-0.2.1.dist-info/RECORD
