Metadata-Version: 2.1
Name: agential
Version: 0.2.1
Summary: A flexible agent library.
Home-page: https://github.com/alckasoc/agential
License: MIT
Keywords: agent,LLM,poetry
Author: Vincent Tu
Author-email: tuvincent0106@gmail.com
Requires-Python: >=3.10,<4.0
Classifier: License :: OSI Approved :: MIT License
Classifier: Programming Language :: Python :: 3
Classifier: Programming Language :: Python :: 3.10
Classifier: Programming Language :: Python :: 3.11
Classifier: Programming Language :: Python :: 3.12
Classifier: Topic :: Scientific/Engineering :: Artificial Intelligence
Requires-Dist: beautifulsoup4 (>=4.12.3,<5.0.0)
Requires-Dist: faiss-cpu (>=1.7.4,<2.0.0)
Requires-Dist: func-timeout (>=4.3.5,<5.0.0)
Requires-Dist: google-api-python-client (>=2.100.0)
Requires-Dist: langchain (>=0.2.1,<0.3.0)
Requires-Dist: langchain-community (>=0.2.1,<0.3.0)
Requires-Dist: langchain-core (>=0.2.3,<0.3.0)
Requires-Dist: litellm (>=1.42.12,<2.0.0)
Requires-Dist: requests (>=2.32.3,<3.0.0)
Requires-Dist: scipy (>=1.13.1,<2.0.0)
Requires-Dist: sentence-transformers (>=2.2.2,<3.0.0)
Requires-Dist: thefuzz (>=0.22.1,<0.23.0)
Requires-Dist: tiktoken (>=0.7.0,<0.8.0)
Requires-Dist: torch (==2.2.0)
Requires-Dist: types-requests (>=2.32.0.20240914,<3.0.0.0)
Requires-Dist: wikipedia (>=1.4.0,<2.0.0)
Project-URL: Repository, https://github.com/alckasoc/agential
